README.md
setup.py
codepod/__init__.py
codepod/console.py
codepod/constants.py
codepod/engine.py
codepod/exceptions.py
codepod/handlers.py
codepod/managers.py
codepod/queues/__init__.py
codepod/queues/abstracts.py
codepod/queues/callbacks.py
codepod/queues/consumers.py
codepod_engine.egg-info/PKG-INFO
codepod_engine.egg-info/SOURCES.txt
codepod_engine.egg-info/dependency_links.txt
codepod_engine.egg-info/entry_points.txt
codepod_engine.egg-info/requires.txt
codepod_engine.egg-info/top_level.txt