Metadata-Version: 2.1
Name: codepod-engine
Version: 0.0.2
Summary: Codepod Engine is a cloud-based compiler engine that can be deployed as a worker that consumes the input and produces the output
Home-page: UNKNOWN
Author: Dr4g0n
License: UNKNOWN
Platform: UNKNOWN
Classifier: Programming Language :: Python :: 3
Classifier: License :: OSI Approved :: MIT License
Classifier: Operating System :: OS Independent
Requires-Python: >=3.6
